vidtoch/__init__.py
vidtoch/__utils__.py
vidtoch-0.4.0.dist-info/LICENSE
vidtoch-0.4.0.dist-info/METADATA
vidtoch-0.4.0.dist-info/WHEEL
vidtoch-0.4.0.dist-info/top_level.txt
vidtoch-0.4.0.dist-info/RECORD
