Metadata-Version: 2.1
Name: vidtoch
Version: 0.4.0
Summary: 一个帮你将视频转为字符视频的模块。
Home-page: https://gitee.com/hrpzcf/vidtoch
Author: hrpzcf
Author-email: hrpzcf@foxmail.com
Maintainer: hrpzcf
Maintainer-email: hrpzcf@foxmail.com
License: MIT License
Keywords: character video,video,character
Platform: UNKNOWN
Classifier: Intended Audience :: Developers
Classifier: Development Status :: 4 - Beta
Classifier: License :: OSI Approved :: MIT License
Classifier: Programming Language :: Python :: 3.7
Classifier: Programming Language :: Python :: 3.8
Classifier: Programming Language :: Python :: 3.9
Requires-Python: >=3.7
License-File: LICENSE
Requires-Dist: opencv-python
Requires-Dist: imgtoch (>=0.2.2)
